option_prices-0.1.0.dist-info/licenses/LICENSE
option_pricings/__init__.py
option_pricings/bsm.py
option_prices-0.1.0.dist-info/METADATA
option_prices-0.1.0.dist-info/WHEEL
option_prices-0.1.0.dist-info/top_level.txt
option_prices-0.1.0.dist-info/RECORD
