Metadata-Version: 2.4
Name: option_prices
Version: 0.1.0
Summary: Option pricing using the Black Scholes Model
Author-email: Shreenivas Dani <shreenivasdani@gmail.com>
License: MIT
Requires-Python: >=3.8
License-File: LICENSE
Requires-Dist: numpy
Requires-Dist: scipy
Dynamic: license-file
